fa_cli/__init__.py
fa_cli/main.py
fa_cli/commands/__init__.py
fa_cli/commands/contents.py
fa_cli/commands/controller.py
fa_cli/commands/migration.py
fa_cli/commands/project.py
fa_cli-1.1.4.dist-info/LICENSE
fa_cli-1.1.4.dist-info/METADATA
fa_cli-1.1.4.dist-info/WHEEL
fa_cli-1.1.4.dist-info/entry_points.txt
fa_cli-1.1.4.dist-info/top_level.txt
fa_cli-1.1.4.dist-info/RECORD
