Metadata-Version: 2.1
Name: fa-cli
Version: 1.1.4
Classifier: Programming Language :: Python :: 3
Classifier: License :: OSI Approved :: MIT License
Classifier: Operating System :: OS Independent
Requires-Python: >=3.6
License-File: LICENSE
Requires-Dist: typer[all]
Requires-Dist: rich
Requires-Dist: gitpython
